MANIFEST.in
README.md
setup.py
docs/38.pdf
docs/DoYouSpeakLondon.pdf
dysl/__init__.py
dysl/dysl.py
dysl/langid.py
dysl/social.py
dysl/utils.py
dysl/version.py
dysl.egg-info/PKG-INFO
dysl.egg-info/SOURCES.txt
dysl.egg-info/dependency_links.txt
dysl.egg-info/not-zip-safe
dysl.egg-info/top_level.txt
dysl/corpora/__init__.py
dysl/corpora/corpus-5langs/ar-latin.txt
dysl/corpora/corpus-5langs/ar.txt
dysl/corpora/corpus-5langs/en.txt
dysl/corpora/corpus-5langs/es.txt
dysl/corpora/corpus-5langs/fr.txt
dysl/corpora/corpus-esaren.test/ar/file1.txt
dysl/corpora/corpus-esaren.test/en/file1.txt
dysl/corpora/corpus-esaren.test/es/file1.txt
dysl/corpora/corpus-esaren.test/unk/file1.txt
dysl/corpora/corpus-esaren/cinema/ar/file1.txt
dysl/corpora/corpus-esaren/cinema/en/file1.txt
dysl/corpora/corpus-esaren/cinema/es/file1.txt
dysl/corpora/corpus-esaren/cinema/pt/file1.txt
dysl/corpora/corpus-esaren/egypt/ar/file1.txt
dysl/corpora/corpus-esaren/egypt/ar/file2.txt
dysl/corpora/corpus-esaren/egypt/en/file1.txt
dysl/corpora/corpus-esaren/egypt/en/file2.txt
dysl/corpora/corpus-esaren/egypt/es/file1.txt
dysl/corpora/corpus-esaren/egypt/es/file2.txt
dysl/corpora/corpus-esaren/egypt/pt/file1.txt
dysl/corpora/corpus-esaren/egypt/pt/file2.txt
dysl/corpora/corpus-esaren/gvo/ar/file1.txt
dysl/corpora/corpus-esaren/gvo/ar/file2.txt
dysl/corpora/corpus-esaren/gvo/ar/file3.txt
dysl/corpora/corpus-esaren/gvo/en/file1.txt
dysl/corpora/corpus-esaren/gvo/en/file2.txt
dysl/corpora/corpus-esaren/gvo/en/file3.txt
dysl/corpora/corpus-esaren/gvo/es/file1.txt
dysl/corpora/corpus-esaren/gvo/es/file2.txt
dysl/corpora/corpus-esaren/gvo/es/file3.txt
dysl/corpora/corpus-esaren/gvo/pt/file1.txt
dysl/corpora/corpus-esaren/gvo/pt/file2.txt
dysl/corpora/corpus-esaren/gvo/pt/file3.txt
dysl/corpora/corpus-esaren/internet/ar/file1.txt
dysl/corpora/corpus-esaren/internet/ar/file2.txt
dysl/corpora/corpus-esaren/internet/ar/file3.txt
dysl/corpora/corpus-esaren/internet/en/file1.txt
dysl/corpora/corpus-esaren/internet/en/file2.txt
dysl/corpora/corpus-esaren/internet/en/file3.txt
dysl/corpora/corpus-esaren/internet/es/file1.txt
