Metadata-Version: 1.0
Name: dysl
Version: 0.13
Summary: Do you speak London?
Home-page: https://github.com/gr33ndata/dysl
Author: Tarek Amr
Author-email: UNKNOWN
License: MIT
Platform: UNKNOWN
